aivim/__init__.py
aivim/ai_service.py
aivim/buffer.py
aivim/command_handler.py
aivim/commands.py
aivim/display.py
aivim/editor.py
aivim/history.py
aivim/key_handler.py
aivim/modes.py
aivim/nlp_mode.py
aivim/run_editor.py
aivim/syntax.py
aivim/ui.py
aivim/utils.py
aivim-0.2.8.dist-info/licenses/LICENSE
aivim-0.2.8.dist-info/METADATA
aivim-0.2.8.dist-info/WHEEL
aivim-0.2.8.dist-info/entry_points.txt
aivim-0.2.8.dist-info/top_level.txt
aivim-0.2.8.dist-info/RECORD
