Metadata-Version: 2.4
Name: aivim
Version: 0.2.8
Summary: AI-enhanced Vim-like text editor with code assistance and generation
Author-email: Daniel Moya <daniel.moya@dimensigon.com>
License: MIT
Project-URL: Homepage, https://github.com/danimoya/AIVim-Editor
Project-URL: Bug Tracker, https://github.com/danimoya/AIVim-Editor/issues
Keywords: vim,editor,ai,code-generation,code-improvement,nlp
Classifier: Development Status :: 4 - Beta
Classifier: Intended Audience :: Developers
Classifier: License :: OSI Approved :: MIT License
Classifier: Programming Language :: Python :: 3
Classifier: Programming Language :: Python :: 3.8
Classifier: Programming Language :: Python :: 3.9
Classifier: Programming Language :: Python :: 3.10
Classifier: Programming Language :: Python :: 3.11
Classifier: Programming Language :: Python :: 3.12
Classifier: Topic :: Text Editors
Classifier: Topic :: Text Editors :: Integrated Development Environments (IDE)
Classifier: Topic :: Software Development
Requires-Python: >=3.8
License-File: LICENSE
Requires-Dist: flask>=2.0.0
Requires-Dist: openai>=1.0.0
Requires-Dist: requests>=2.25.0
Requires-Dist: windows-curses>=2.3.0; platform_system == "Windows"
Dynamic: license-file
